README.md
setup.py
StravaAnalysis/__init__.py
StravaAnalysis/data_aggregator.py
StravaAnalysis/data_collection.py
StravaAnalysis/data_export.py
StravaAnalysis/data_import.py
StravaAnalysis/test_environment.py
StravaAnalysis.egg-info/PKG-INFO
StravaAnalysis.egg-info/SOURCES.txt
StravaAnalysis.egg-info/dependency_links.txt
StravaAnalysis.egg-info/top_level.txt