Metadata-Version: 2.1
Name: StravaAnalysis
Version: 0.1.4
Summary: Fully automates the collection of Strava data via their API and neatly structures this inside json files per activity.
Home-page: https://github.com/JerBouma/StravaAnalysis
Author: JerBouma
Author-email: jer.bouma@gmail.com
License: MIT
Keywords: strava,analysis,api
Platform: UNKNOWN
Classifier: Development Status :: 5 - Production/Stable
Classifier: Intended Audience :: Developers
Classifier: Topic :: Utilities
Classifier: License :: OSI Approved :: MIT License
Classifier: Operating System :: OS Independent
Classifier: Programming Language :: Python :: 3
